specfab.libs/libgfortran-040039e1.so.5.0.0
specfab.libs/libspecfab-bc9156af.so
specfab.libs/libgfortran-91cc3cb1.so.3.0.0
specfab.libs/liblapack-1ad85175.so.3.4.2
specfab.libs/libblas-357956a1.so.3.4.2
specfab.libs/libz-745e0a09.so.1.2.7
specfab.libs/libquadmath-96973f99.so.0.0.0
specfab.libs/libfftw3-17cc48a2.so.3.3.2
specfab/specfabpy.cpython-37m-x86_64-linux-gnu.so
specfab/__init__.py
specfab-1.0.1.dist-info/LICENSE
specfab-1.0.1.dist-info/METADATA
specfab-1.0.1.dist-info/top_level.txt
specfab-1.0.1.dist-info/RECORD
specfab-1.0.1.dist-info/WHEEL
