Metadata-Version: 2.1
Name: specfab
Version: 1.0.1
Summary: This is a python version of Specfab
Home-page: UNKNOWN
License: UNKNOWN
Platform: UNKNOWN
License-File: LICENSE
